lazy_set/__init__.py
lazy_set/lazy_set.py
lazy_set-1.4.6.dist-info/METADATA
lazy_set-1.4.6.dist-info/RECORD
lazy_set-1.4.6.dist-info/WHEEL
lazy_set-1.4.6.dist-info/top_level.txt
