Metadata-Version: 2.1
Name: lazy-set
Version: 1.4.6
Summary: A collection that tries to imitate a "lazy" difference and union of sets.
Home-page: https://github.com/AvivYaish/LazySet
Author: Aviv Yaish
Author-email: aviv.yaish@mail.huji.ac.il
License: UNKNOWN
Platform: UNKNOWN
Requires-Python: >=3.6
